MANIFEST.in
README.html
README.rst
setup.py
asms/__init__.py
asms.egg-info/PKG-INFO
asms.egg-info/SOURCES.txt
asms.egg-info/dependency_links.txt
asms.egg-info/not-zip-safe
asms.egg-info/top_level.txt
bin/sms.py